tidocs-1.1.0.dist-info/METADATA
tidocs-1.1.0.dist-info/WHEEL
tidocs-1.1.0.dist-info/entry_points.txt
tidocs-1.1.0.dist-info/licenses/LICENSE
tidocs/VERSION
tidocs/__init__.py
tidocs/__version__.py
tidocs/cli.py
tidocs/docx_handler.py
tidocs/markdown_handler.py
tidocs/markdown_to_docx.py
tidocs/merge/main_marimo.py
tidocs/pandoc_wrapper.py
tidocs/resources/custom-pdf-reference.docx
tidocs/util.py
tidocs-1.1.0.dist-info/RECORD
