Metadata-Version: 2.1
Name: tidocs
Version: 1.1.0
Summary: A suite of utilities designed to streamline TiDB documentation workflows.
Author-Email: Aolin <aolinz@outlook.com>
License: Apache-2.0
Requires-Python: >=3.9
Requires-Dist: marimo>=0.9.20
Requires-Dist: platformdirs>=4.3.6
Requires-Dist: python-docx>=1.1.2
Requires-Dist: pyyaml>=6.0.2
Requires-Dist: hypercorn>=0.17.3
Requires-Dist: rich>=13.9.4
Requires-Dist: pydantic>=2.10.4
